{
  "type": "Feature",
  "properties": {
    "date:inception_lower": "2020-01-23",
    "date:inception_upper": "2020-01-23",
    "flysfo:airline_code": "JX",
    "flysfo:is_sfo": 1,
    "sfomuseum:placetype": "airline",
    "wof:name": "Starlux Airlines",
    "wof:placetype": "custom",
    "wof:placetype_alt": [
      "airline"
    ]
  },
  "geometry": {"coordinates":[121.549514,25.058464],"type":"Point"}
}
