{
  "type": "Feature",
  "properties": {
    "date:inception_lower": "1979-01-01",
    "date:inception_upper": "1979-12-31",
    "iso:country": "LS",
    "sfomuseum:is_sfo": 1,
    "sfomuseum:placetype": "company",
    "wd:airline_hub": [
      "Q645462"
    ],
    "wd:country": "Q1013",
    "wd:instance_of": [
      "Q46970"
    ],
    "wof:brand_name": "Lesotho Airways",
    "wof:name": "Lesotho Airways",
    "wof:placetype": "custom",
    "wof:placetype_alt": [
      "company"
    ]
  },
  "geometry": {"coordinates":[28.163744,-29.516751],"type":"Point"}
}
