{
  "type": "Feature",
  "properties": {
    "date:inception_lower": "1946-01-01",
    "date:inception_upper": "1946-12-31",
    "iso:country": "NI",
    "millsfield:count_images": 1,
    "millsfield:count_objects": 2,
    "sfomuseum:count_objects_public": 1,
    "sfomuseum:is_sfo": 1,
    "sfomuseum:label": "Lanica Airlines",
    "sfomuseum:name": "Lanica Airlines",
    "sfomuseum:placetype": "airline",
    "wof:name": "Lanica Airlines",
    "wof:placetype": "custom",
    "wof:placetype_alt": "airline",
    "wof:subordinate_of": [
      1159287575
    ]
  },
  "geometry": {"coordinates":[-85.039545,12.793313],"type":"Point"}
}
