{
  "type": "Feature",
  "properties": {
    "iso:country": "US",
    "millsfield:count_images": 6,
    "millsfield:count_objects": 3,
    "sfomuseum:count_objects_public": 3,
    "sfomuseum:is_sfo": 1,
    "sfomuseum:label": "Skystream Airlines",
    "sfomuseum:name": "Skystream Airlines",
    "sfomuseum:placetype": "airline",
    "wof:name": "Skystream Airlines",
    "wof:placetype": "custom",
    "wof:placetype_alt": "airline",
    "wof:subordinate_of": [
      1159288339
    ]
  },
  "geometry": {"coordinates":[-96.999668,39.715956],"type":"Point"}
}
