{
  "type": "Feature",
  "properties": {
    "date:inception_lower": "1955-01-01",
    "date:inception_upper": "1955-12-31",
    "iso:country": "PK",
    "millsfield:count_images": 12,
    "millsfield:count_objects": 6,
    "sfomuseum:is_sfo": 1,
    "sfomuseum:placetype": "company",
    "wd:airline_hub": [
      "Q61052",
      "Q60879",
      "Q816717"
    ],
    "wd:country": "Q843",
    "wd:headquarters": "Q61052",
    "wd:instance_of": [
      "Q46970"
    ],
    "wof:brand_name": "Pakistan International Airlines",
    "wof:name": "Pakistan International Airlines",
    "wof:placetype": "custom",
    "wof:placetype_alt": "company"
  },
  "geometry": {"coordinates":[68.560265,29.329836],"type":"Point"}
}
