{
  "type": "Feature",
  "properties": {
    "date:inception_lower": "1981-01-01",
    "date:inception_upper": "1981-12-31",
    "iso:country": "BT",
    "millsfield:count_images": 1,
    "millsfield:count_objects": 1,
    "sfomuseum:is_sfo": 1,
    "sfomuseum:placetype": "company",
    "wd:airline_hub": [
      "Q44877"
    ],
    "wd:country": "Q917",
    "wd:instance_of": [
      "Q46970"
    ],
    "wof:brand_name": "Druck Air (Royal Bhutan Airlines)",
    "wof:name": "Druck Air (Royal Bhutan Airlines)",
    "wof:placetype": "custom",
    "wof:placetype_alt": "company"
  },
  "geometry": {"coordinates":[89.92561,27.454772],"type":"Point"}
}
