{
  "type": "Feature",
  "properties": {
    "date:inception_lower": "1919-01-01",
    "date:inception_upper": "1919-12-31",
    "iso:country": "CO",
    "millsfield:count_images": 11,
    "millsfield:count_objects": 15,
    "name:unk_x_preferred": [
      "SCADTA (Sociedad Colombo Alemana de Transporte Aéreo)"
    ],
    "sfomuseum:is_sfo": 1,
    "sfomuseum:placetype": "company",
    "wd:country": "Q739",
    "wd:headquarters": "Q62823",
    "wd:instance_of": [
      "Q46970"
    ],
    "wof:brand_name": "SCADTA (Sociedad Colombo Alemana de Transporte Aereo)",
    "wof:name": "SCADTA (Sociedad Colombo Alemana de Transporte Aereo)",
    "wof:placetype": "custom",
    "wof:placetype_alt": "company"
  },
  "geometry": {"coordinates":[-73.166783,3.420497],"type":"Point"}
}
