{
  "type": "Feature",
  "properties": {
    "date:inception_lower": "1926-01-01",
    "date:inception_upper": "1926-12-31",
    "iso:country": "DE",
    "sfomuseum:count_objects_public": 0,
    "sfomuseum:is_sfo": 1,
    "sfomuseum:placetype": "company",
    "wd:country": "Q183",
    "wd:instance_of": [
      "Q936518"
    ],
    "wof:brand_name": "Klemm",
    "wof:name": "Klemm",
    "wof:placetype": "custom",
    "wof:placetype_alt": "company"
  },
  "geometry": {"coordinates":[9.62743,51.196755],"type":"Point"}
}
