{
  "type": "Feature",
  "properties": {
    "iso:country": "GY",
    "millsfield:count_images": 2,
    "millsfield:count_objects": 2,
    "sfomuseum:count_objects_public": 1,
    "sfomuseum:is_sfo": 1,
    "sfomuseum:label": "Guyana Air 2000",
    "sfomuseum:name": "Guyana Air 2000",
    "sfomuseum:placetype": "airline",
    "wof:name": "Guyana Air 2000",
    "wof:placetype": "custom",
    "wof:placetype_alt": [
      "airline"
    ],
    "wof:subordinate_of": [
      1159287265
    ]
  },
  "geometry": {"coordinates":[-58.912352,5.121996],"type":"Point"}
}
