{
  "type": "Feature",
  "properties": {
    "date:inception_lower":"1945-01-01",
    "date:inception_upper":"1945-12-31",
    "sfomuseum:is_sfo":1,
    "sfomuseum:label":"TAP (Transportes Aereos Portugueses)  (TAP Air Portugal)",
    "sfomuseum:name":"TAP (Transportes Aereos Portugueses)",
    "sfomuseum:placetype":"airline",
    "wof:name":"TAP (Transportes Aereos Portugueses)",
    "wof:placetype":"enterprise",
    "wof:subordinate_of":[
        1159287519
    ]
},
  "geometry": {"coordinates":[-9.135591,38.772844],"type":"Point"}
}