{
  "type": "Feature",
  "properties": {
    "date:inception_lower": "1964-01-01",
    "date:inception_upper": "1964-12-31",
    "iso:country": "SG",
    "millsfield:count_images": 231,
    "millsfield:count_objects": 190,
    "sfomuseum:is_sfo": 1,
    "sfomuseum:placetype": "company",
    "wd:airline_hub": [
      "Q32159"
    ],
    "wd:country": "Q334",
    "wd:headquarters": "Q334",
    "wd:instance_of": [
      "Q46970"
    ],
    "wof:brand_name": "Singapore Airlines",
    "wof:name": "Singapore Airlines",
    "wof:placetype": "custom",
    "wof:placetype_alt": [
      "company"
    ]
  },
  "geometry": {"coordinates":[103.833828,1.316382],"type":"Point"}
}
