{
  "type": "Feature",
  "properties": {
    "date:inception_lower": "1984-01-01",
    "date:inception_upper": "1984-12-31",
    "iso:country": "CN",
    "sfomuseum:is_sfo": 1,
    "sfomuseum:placetype": "company",
    "wd:airline_hub": [
      "Q177216"
    ],
    "wd:country": "Q148",
    "wd:headquarters": "Q68744",
    "wd:instance_of": [
      "Q46970"
    ],
    "wof:brand_name": "Xiamen Airlines",
    "wof:name": "Xiamen Airlines",
    "wof:placetype": "enterprise"
  },
  "geometry": {"coordinates":[118.103833,24.489945],"type":"Point"}
}
