{
  "type": "Feature",
  "properties": {
    "date:inception_lower": "1929-01-01",
    "date:inception_upper": "1929-12-31",
    "flysfo:airline_code": "HA",
    "flysfo:is_sfo": 1,
    "iso:country": "US",
    "millsfield:count_images": 338,
    "millsfield:count_objects": 245,
    "sfomuseum:count_objects_public": 52,
    "sfomuseum:hashtags": [
      "hawaiianairlines"
    ],
    "sfomuseum:is_sfo": 1,
    "sfomuseum:label": "Hawaiian Airlines",
    "sfomuseum:name": "Hawaiian Airlines",
    "sfomuseum:placetype": "airline",
    "wd:airline_hub": [
      "Q531178",
      "Q1431637"
    ],
    "wd:country": "Q30",
    "wd:headquarters": "Q18094",
    "wd:instance_of": [
      "Q46970"
    ],
    "wof:name": "Hawaiian Airlines",
    "wof:placetype": "custom",
    "wof:placetype_alt": [
      "airline"
    ],
    "wof:subordinate_of": [
      1159287913
    ]
  },
  "geometry": {"coordinates":[-157.859944,21.308822],"type":"Point"}
}
