{
  "type": "Feature",
  "properties": {
    "iso:country": "US",
    "millsfield:count_images": 275,
    "millsfield:count_objects": 213,
    "sfomuseum:is_sfo": 1,
    "sfomuseum:placetype": "company",
    "wof:brand_name": "National Airlines",
    "wof:name": "National Airlines",
    "wof:placetype": "custom",
    "wof:placetype_alt": [
      "company"
    ]
  },
  "geometry": {"coordinates":[-96.999668,39.715956],"type":"Point"}
}
