{
  "type": "Feature",
  "properties": {
    "date:inception_lower":"1919-01-01",
    "date:inception_upper":"1919-12-31",
    "iso:country":"CO",
    "sfomuseum:is_sfo":1,
    "sfomuseum:label":"Avianca  (Avianca Airlines)",
    "sfomuseum:name":"Avianca",
    "sfomuseum:placetype":"airline",
    "wd:airline_hub":[
        "Q201785"
    ],
    "wd:country":"Q739",
    "wd:headquarters":"Q2841",
    "wd:instance_of":[
        "Q46970"
    ],
    "wof:name":"Avianca",
    "wof:placetype":"enterprise",
    "wof:subordinate_of":[
        1159287217
    ]
},
  "geometry": {"coordinates":[-74.08768000000001,4.635456],"type":"Point"}
}