{
  "type": "Feature",
  "properties": {
    "date:cessation_lower": "1986-01-01",
    "date:cessation_upper": "1986-12-31",
    "date:inception_lower": "1966-01-01",
    "date:inception_upper": "1966-12-31",
    "iso:country": "US",
    "millsfield:count_images": 1,
    "millsfield:count_objects": 1,
    "sfomuseum:brand": "Summit Airlines",
    "sfomuseum:count_objects_public": 0,
    "sfomuseum:country": "USA",
    "sfomuseum:hub": "Philadelphia",
    "sfomuseum:is_sfo": 1,
    "sfomuseum:label": "Summit Airlines",
    "sfomuseum:name": "Summit Airlines",
    "sfomuseum:placetype": "airline",
    "wof:name": "Summit Airlines",
    "wof:placetype": "custom",
    "wof:placetype_alt": [
      "airline"
    ]
  },
  "geometry": {"coordinates":[-96.999668,39.715956],"type":"Point"}
}
