{
  "type": "Feature",
  "properties": {
    "date:inception_lower": "1933-01-01",
    "date:inception_upper": "1933-12-31",
    "flysfo:airline_code": "AF",
    "flysfo:is_sfo": 1,
    "millsfield:count_images": 476,
    "millsfield:count_objects": 309,
    "sfomuseum:brand": "Air France",
    "sfomuseum:count_objects_public": 77,
    "sfomuseum:hashtags": [
      "airfrance"
    ],
    "sfomuseum:is_sfo": 1,
    "sfomuseum:label": "Air France",
    "sfomuseum:name": "Air France",
    "sfomuseum:placetype": "airline",
    "wd:airline_hub": [
      "Q46280",
      "Q223416",
      "Q1547",
      "Q651190",
      "Q821557",
      "Q372615"
    ],
    "wd:country": "Q142",
    "wd:headquarters": "Q46280",
    "wd:instance_of": [
      "Q46970"
    ],
    "wof:name": "Air France",
    "wof:placetype": "custom",
    "wof:placetype_alt": "airline",
    "wof:subordinate_of": [
      1360700617
    ]
  },
  "geometry": {"coordinates":[2.542809,49.007854],"type":"Point"}
}
