{
  "type": "Feature",
  "properties": {
    "date:inception_lower": "1999-01-01",
    "date:inception_upper": "1999-12-31",
    "flysfo:airline_code": "MT",
    "flysfo:is_sfo": 1,
    "iso:country": "GB",
    "millsfield:count_images": 3,
    "millsfield:count_objects": 2,
    "sfomuseum:count_objects_public": 1,
    "sfomuseum:country": "England",
    "sfomuseum:hub": "Manchester",
    "sfomuseum:is_sfo": 1,
    "sfomuseum:label": "Thomas Cook Airlines",
    "sfomuseum:name": "Thomas Cook Airlines",
    "sfomuseum:placetype": "airline",
    "wd:country": "Q145",
    "wd:headquarters": "Q18125",
    "wd:instance_of": [
      "Q46970"
    ],
    "wof:name": "Thomas Cook Airlines",
    "wof:placetype": "custom",
    "wof:placetype_alt": [
      "airline"
    ],
    "wof:subordinate_of": [
      1159288177
    ]
  },
  "geometry": {"type":"Point","coordinates":[-1.247349,52.418788]}
}
