{
  "type": "Feature",
  "properties": {
    "iso:country": "MA",
    "sfomuseum:count_objects_public": 0,
    "sfomuseum:is_sfo": 1,
    "sfomuseum:label": "Air Atlas",
    "sfomuseum:name": "Air Atlas",
    "sfomuseum:placetype": "airline",
    "wd:instance_of": [
      "Q46970"
    ],
    "wof:name": "Air Atlas",
    "wof:placetype": "enterprise",
    "wof:subordinate_of": [
      1159288373
    ]
  },
  "geometry": {"coordinates":[-7.189711,31.649504],"type":"Point"}
}
