{
  "type": "Feature",
  "properties": {
    "date:inception_lower": "1932-01-01",
    "date:inception_upper": "1932-12-31",
    "iso:country": "DE",
    "sfomuseum:is_sfo": 1,
    "sfomuseum:placetype": "company",
    "wd:country": "Q30",
    "wd:headquarters": "Q2749",
    "wd:instance_of": [
      "Q936518"
    ],
    "wof:brand_name": "Beechcraft",
    "wof:name": "Beechcraft",
    "wof:placetype": "enterprise"
  },
  "geometry": {"coordinates":[10.896842,48.369338],"type":"Point"}
}
