{
  "type": "Feature",
  "properties": {
    "date:inception_lower": "1920-01-01",
    "date:inception_upper": "1920-12-31",
    "iso:country": "NZ",
    "millsfield:count_images": 3,
    "millsfield:count_objects": 4,
    "sfomuseum:is_sfo": 1,
    "sfomuseum:placetype": "company",
    "wd:airline_hub": [
      "Q1061330",
      "Q1150574"
    ],
    "wd:country": "Q664",
    "wd:headquarters": "Q79990",
    "wd:instance_of": [
      "Q46970"
    ],
    "wof:brand_name": "Mount Cook Airlines",
    "wof:name": "Mount Cook Airlines",
    "wof:placetype": "custom",
    "wof:placetype_alt": "company"
  },
  "geometry": {"coordinates":[172.610876,-43.517364],"type":"Point"}
}
