{
  "type": "Feature",
  "properties": {
    "date:inception_lower": "1987-01-01",
    "date:inception_upper": "1987-12-31",
    "iso:country": "MX",
    "millsfield:count_objects": 2,
    "sfomuseum:count_objects_public": 2,
    "sfomuseum:is_sfo": 1,
    "sfomuseum:label": "Aeromar",
    "sfomuseum:name": "Aeromar",
    "sfomuseum:placetype": "airline",
    "wd:country": "Q96",
    "wd:instance_of": [
      "Q46970"
    ],
    "wof:name": "Aeromar",
    "wof:placetype": "custom",
    "wof:placetype_alt": "airline",
    "wof:subordinate_of": [
      1159286863
    ]
  },
  "geometry": {"coordinates":[-102.289691,23.920061],"type":"Point"}
}
