{
  "type": "Feature",
  "properties": {
    "date:inception_lower":"1990-01-01",
    "date:inception_upper":"1990-12-31",
    "iso:country":"CN",
    "sfomuseum:is_sfo":1,
    "sfomuseum:placetype":"company",
    "wd:airline_hub":[
        "Q1144167"
    ],
    "wd:country":"Q148",
    "wd:headquarters":"Q11720",
    "wd:instance_of":[
        "Q46970"
    ],
    "wof:brand_name":"China Northern Airlines",
    "wof:name":"China Northern Airlines",
    "wof:placetype":"enterprise"
},
  "geometry": {"coordinates":[123.42689799999999,41.800541],"type":"Point"}
}