{
  "type": "Feature",
  "properties": {
    "date:inception_lower": "1932-01-01",
    "date:inception_upper": "1932-12-31",
    "iso:country": "RU",
    "millsfield:count_images": 145,
    "millsfield:count_objects": 83,
    "sfomuseum:is_sfo": 1,
    "sfomuseum:placetype": "company",
    "wd:airline_hub": [
      "Q192733",
      "Q649"
    ],
    "wd:country": "Q159",
    "wd:headquarters": "Q649",
    "wd:instance_of": [
      "Q46970",
      "Q270791"
    ],
    "wof:brand_name": "Aeroflot Russian Airlines",
    "wof:name": "Aeroflot Russian Airlines",
    "wof:placetype": "custom",
    "wof:placetype_alt": "company"
  },
  "geometry": {"coordinates":[37.615561,55.741469],"type":"Point"}
}
