{
  "type": "Feature",
  "properties": {
    "date:inception_lower":"1948-01-01",
    "date:inception_upper":"1948-12-31",
    "iso:country":"LU",
    "sfomuseum:is_sfo":1,
    "sfomuseum:label":"Luxair",
    "sfomuseum:name":"Luxair",
    "sfomuseum:placetype":"airline",
    "wd:airline_hub":[
        "Q872186"
    ],
    "wd:country":"Q32",
    "wd:headquarters":"Q985476",
    "wd:instance_of":[
        "Q46970"
    ],
    "wof:name":"Luxair",
    "wof:placetype":"enterprise",
    "wof:subordinate_of":[
        1159287253
    ]
},
  "geometry": {"coordinates":[6.21889,49.61333],"type":"Point"}
}