{
  "type": "Feature",
  "properties": {
    "date:inception_lower": "2008-01-01",
    "date:inception_upper": "2008-12-31",
    "flysfo:airline_code": "AD",
    "flysfo:is_sfo": 1,
    "sfomuseum:placetype": "airline",
    "wof:name": "Azul Brazilian Airlines",
    "wof:placetype": "custom"
  },
  "geometry": {"coordinates":[-46.847052,-23.496212],"type":"Point"}
}
