{
  "type": "Feature",
  "properties": {
    "date:inception_lower": "1926-01-01",
    "date:inception_upper": "1926-12-31",
    "flysfo:airline_code": "LH",
    "flysfo:is_sfo": 1,
    "iso:country": "DE",
    "millsfield:count_images": 607,
    "millsfield:count_objects": 454,
    "sfomuseum:airline_role": "cargo",
    "sfomuseum:count_objects_public": 143,
    "sfomuseum:hashtags": [
      "lufthansa"
    ],
    "sfomuseum:is_sfo": 1,
    "sfomuseum:label": "Lufthansa  (Lufthansa German Airlines)",
    "sfomuseum:name": "Lufthansa",
    "sfomuseum:placetype": "airline",
    "wd:airline_hub": [
      "Q58226",
      "Q46033",
      "Q131402"
    ],
    "wd:country": "Q183",
    "wd:headquarters": "Q365",
    "wd:instance_of": [
      "Q46970"
    ],
    "wof:name": "Lufthansa",
    "wof:placetype": "custom",
    "wof:placetype_alt": "airline",
    "wof:subordinate_of": [
      1159288215
    ]
  },
  "geometry": {"coordinates":[6.934628,50.94718],"type":"Point"}
}
