{
  "type": "Feature",
  "properties": {
    "date:inception_lower":"1946-01-01",
    "date:inception_upper":"1946-12-31",
    "iso:country":"NG",
    "sfomuseum:is_sfo":1,
    "sfomuseum:placetype":"company",
    "wd:airline_hub":[
        "Q1043631"
    ],
    "wd:country":"Q1033",
    "wd:instance_of":[
        "Q46970"
    ],
    "wof:brand_name":"West African Airways Corporation",
    "wof:name":"West African Airways Corporation",
    "wof:placetype":"enterprise"
},
  "geometry": {"coordinates":[7.607418,9.404974],"type":"Point"}
}