{
  "type": "Feature",
  "properties": {
    "date:inception_lower": "1961-01-01",
    "date:inception_upper": "1961-12-31",
    "iso:country": "IR",
    "millsfield:count_images": 32,
    "millsfield:count_objects": 21,
    "sfomuseum:is_sfo": 1,
    "sfomuseum:placetype": "company",
    "wd:airline_hub": [
      "Q734729",
      "Q513684"
    ],
    "wd:country": "Q794",
    "wd:headquarters": "Q3616",
    "wd:instance_of": [
      "Q46970"
    ],
    "wof:brand_name": "Iran Air",
    "wof:name": "Iran Air",
    "wof:placetype": "custom",
    "wof:placetype_alt": "company"
  },
  "geometry": {"coordinates":[51.42151,35.69439],"type":"Point"}
}
