{
  "type": "Feature",
  "properties": {
    "date:inception_lower":"1989-01-01",
    "date:inception_upper":"1989-12-31",
    "iso:country":"TR",
    "sfomuseum:count_objects_public":0,
    "sfomuseum:is_sfo":1,
    "sfomuseum:label":"Pegasus Airlines",
    "sfomuseum:name":"Pegasus Airlines",
    "sfomuseum:placetype":"airline",
    "wd:airline_hub":[
        "Q723622"
    ],
    "wd:country":"Q43",
    "wd:headquarters":"Q406",
    "wd:instance_of":[
        "Q46970"
    ],
    "wof:name":"Pegasus Airlines",
    "wof:placetype":"enterprise",
    "wof:subordinate_of":[
        1159287843
    ]
},
  "geometry": {"coordinates":[28.94966,41.01384],"type":"Point"}
}