{
  "type": "Feature",
  "properties": {
    "date:inception_lower":"1933-01-01",
    "date:inception_upper":"1933-12-31",
    "iso:country":"BR",
    "sfomuseum:is_sfo":1,
    "sfomuseum:placetype":"company",
    "wd:airline_hub":[
        "Q862401"
    ],
    "wd:country":"Q155",
    "wd:instance_of":[
        "Q46970"
    ],
    "wof:brand_name":"VASP",
    "wof:name":"VASP",
    "wof:placetype":"enterprise"
},
  "geometry": {"coordinates":[-49.542449,-11.928923],"type":"Point"}
}