{
  "type": "Feature",
  "properties": {
    "date:inception_lower": "1995-01-01",
    "date:inception_upper": "1995-12-31",
    "iso:country": "EG",
    "millsfield:count_images": 1,
    "millsfield:count_objects": 1,
    "sfomuseum:count_objects_public": 0,
    "sfomuseum:is_sfo": 1,
    "sfomuseum:label": "Palestinian Airlines",
    "sfomuseum:name": "Palestinian Airlines",
    "sfomuseum:placetype": "airline",
    "wd:airline_hub": [
      "Q201626"
    ],
    "wd:country": "Q79",
    "wd:headquarters": "Q238452",
    "wd:instance_of": [
      "Q46970"
    ],
    "wof:name": "Palestinian Airlines",
    "wof:placetype": "custom",
    "wof:placetype_alt": [
      "airline"
    ],
    "wof:subordinate_of": [
      1159288653
    ]
  },
  "geometry": {"coordinates":[33.79844,31.13159],"type":"Point"}
}
