{
  "type": "Feature",
  "properties": {
    "iso:country": "GB",
    "sfomuseum:count_objects_public": 0,
    "sfomuseum:is_sfo": 1,
    "sfomuseum:placetype": "company",
    "wd:country": "Q145",
    "wd:instance_of": [
      "Q3957"
    ],
    "wof:brand_name": "Blackburn",
    "wof:name": "Blackburn",
    "wof:placetype": "custom",
    "wof:placetype_alt": "company"
  },
  "geometry": {"coordinates":[-1.247349,52.418788],"type":"Point"}
}
