{
  "type": "Feature",
  "properties": {
    "iso:country":"GB",
    "sfomuseum:is_sfo":1,
    "sfomuseum:placetype":"company",
    "wd:country":"Q145",
    "wd:instance_of":[
        "Q3957"
    ],
    "wof:brand_name":"Blackburn",
    "wof:name":"Blackburn",
    "wof:placetype":"enterprise"
},
  "geometry": {"coordinates":[-1.247349,52.418788],"type":"Point"}
}