{
  "type": "Feature",
  "properties": {
    "date:inception_lower":"1953-01-01",
    "date:inception_upper":"1953-12-31",
    "iso:country":"LB",
    "sfomuseum:is_sfo":1,
    "sfomuseum:label":"Trans Mediterranean Airways",
    "sfomuseum:name":"Trans Mediterranean Airways",
    "sfomuseum:placetype":"airline",
    "wd:airline_hub":[
        "Q668329"
    ],
    "wd:country":"Q822",
    "wd:headquarters":"Q3820",
    "wd:instance_of":[
        "Q46970"
    ],
    "wof:name":"Trans Mediterranean Airways",
    "wof:placetype":"enterprise",
    "wof:subordinate_of":[
        1159288639
    ]
},
  "geometry": {"coordinates":[35.49442,33.88894],"type":"Point"}
}