{
  "type": "Feature",
  "properties": {
    "date:inception_lower": "1989-01-01",
    "date:inception_upper": "1989-12-31",
    "iso:country": "TR",
    "sfomuseum:is_sfo": 1,
    "sfomuseum:placetype": "company",
    "wd:airline_hub": [
      "Q827480",
      "Q504382",
      "Q723622"
    ],
    "wd:country": "Q43",
    "wd:headquarters": "Q6487",
    "wd:instance_of": [
      "Q46970"
    ],
    "wof:brand_name": "SunExpress Airlines",
    "wof:name": "SunExpress Airlines",
    "wof:placetype": "enterprise"
  },
  "geometry": {"coordinates":[34.51052,39.339547],"type":"Point"}
}
