{
  "type": "Feature",
  "properties": {
    "date:inception_lower": "2010-01-01",
    "date:inception_upper": "2010-12-31",
    "iso:country": "BD",
    "sfomuseum:is_sfo": 1,
    "sfomuseum:placetype": "company",
    "wd:airline_hub": [
      "Q30603"
    ],
    "wd:country": "Q902",
    "wd:headquarters": "Q1354",
    "wd:instance_of": [
      "Q46970"
    ],
    "wof:brand_name": "Regent Air",
    "wof:name": "Regent Air",
    "wof:placetype": "custom",
    "wof:placetype_alt": [
      "company"
    ]
  },
  "geometry": {"coordinates":[90.032723,24.045958],"type":"Point"}
}
