{
  "type": "Feature",
  "properties": {
    "date:inception_lower":"1969-01-01",
    "date:inception_upper":"1969-12-31",
    "iso:country":"GB",
    "sfomuseum:count_objects_public":0,
    "sfomuseum:country":"UK",
    "sfomuseum:is_sfo":1,
    "sfomuseum:label":"Air Atlantique",
    "sfomuseum:name":"Air Atlantique",
    "sfomuseum:placetype":"airline",
    "wd:airline_hub":[
        "Q1431133"
    ],
    "wd:country":"Q145",
    "wd:instance_of":[
        "Q46970"
    ],
    "wof:name":"Air Atlantique",
    "wof:placetype":"enterprise",
    "wof:subordinate_of":[
        1159286997
    ]
},
  "geometry": {"coordinates":[-1.247349,52.418788],"type":"Point"}
}