{
  "type": "Feature",
  "properties": {
    "date:inception_lower": "1995-01-01",
    "date:inception_upper": "1995-12-31",
    "sfomuseum:is_sfo": 1,
    "sfomuseum:placetype": "company",
    "wd:airline_hub": [
      "Q46280"
    ],
    "wd:country": "Q142",
    "wd:headquarters": "Q46280",
    "wd:instance_of": [
      "Q46970"
    ],
    "wof:brand_name": "XL Airways France",
    "wof:name": "XL Airways France",
    "wof:placetype": "enterprise"
  },
  "geometry": {"coordinates":[2.542809,49.007854],"type":"Point"}
}
