{
  "type": "Feature",
  "properties": {
    "date:inception_lower": "1954-01-01",
    "date:inception_upper": "1954-12-31",
    "iso:country": "KW",
    "sfomuseum:count_objects_public": 0,
    "sfomuseum:is_sfo": 1,
    "sfomuseum:label": "Kuwait Air  (Kuwait Airways)",
    "sfomuseum:name": "Kuwait Air",
    "sfomuseum:placetype": "airline",
    "wof:name": "Kuwait Air",
    "wof:placetype": "enterprise",
    "wof:subordinate_of": [
      1159288633
    ]
  },
  "geometry": {"coordinates":[47.97833,29.36972],"type":"Point"}
}
