{
  "type": "Feature",
  "properties": {
    "date:inception_lower": "1974-01-01",
    "date:inception_upper": "1974-12-31",
    "iso:country": "FR",
    "millsfield:count_images": 3,
    "millsfield:count_objects": 1,
    "sfomuseum:is_sfo": 1,
    "sfomuseum:placetype": "company",
    "wd:airline_hub": [
      "Q17430"
    ],
    "wd:country": "Q142",
    "wd:headquarters": "Q47045",
    "wd:instance_of": [
      "Q46970"
    ],
    "wof:brand_name": "Air Austral",
    "wof:name": "Air Austral",
    "wof:placetype": "custom",
    "wof:placetype_alt": "company"
  },
  "geometry": {"coordinates":[2.549047,46.698481],"type":"Point"}
}
