{
  "type": "Feature",
  "properties": {
    "date:inception_lower": "1994-01-01",
    "date:inception_upper": "1994-12-31",
    "iso:country": "NZ",
    "sfomuseum:count_objects_public": 0,
    "sfomuseum:country": "New Zealand",
    "sfomuseum:is_sfo": 1,
    "sfomuseum:label": "Kiwi Travel International Airlines",
    "sfomuseum:name": "Kiwi Travel International Airlines",
    "sfomuseum:placetype": "airline",
    "wd:airline_hub": [
      "Q1368739"
    ],
    "wd:country": "Q664",
    "wd:instance_of": [
      "Q46970"
    ],
    "wof:name": "Kiwi Travel International Airlines",
    "wof:placetype": "custom",
    "wof:placetype_alt": [
      "airline"
    ],
    "wof:subordinate_of": [
      1159288171
    ]
  },
  "geometry": {"coordinates":[169.232531,-45.175323],"type":"Point"}
}
