{
  "type": "Feature",
  "properties": {
    "date:inception_lower": "1989-01-01",
    "date:inception_upper": "1989-12-31",
    "iso:country": "CN",
    "millsfield:count_images": 2,
    "millsfield:count_objects": 2,
    "sfomuseum:is_sfo": 1,
    "sfomuseum:placetype": "company",
    "wd:airline_hub": [
      "Q1143116",
      "Q32190"
    ],
    "wd:country": "Q148",
    "wd:headquarters": "Q189823",
    "wd:instance_of": [
      "Q46970"
    ],
    "wof:brand_name": "Hainan Airlines",
    "wof:name": "Hainan Airlines",
    "wof:placetype": "custom",
    "wof:placetype_alt": "company"
  },
  "geometry": {"coordinates":[110.32795,20.035308],"type":"Point"}
}
