{
  "type": "Feature",
  "properties": {
    "date:inception_lower":"1957-01-01",
    "date:inception_upper":"1957-12-31",
    "iso:country":"EC",
    "sfomuseum:brand":"Ecuatoriana de Aviaci\u00f3n",
    "sfomuseum:is_sfo":1,
    "sfomuseum:label":"Ecuatoriana Jet Cargo  (Ecuatoriana de Aviaci\u00f3n)",
    "sfomuseum:name":"Ecuatoriana Jet Cargo",
    "sfomuseum:placetype":"airline",
    "wof:name":"Ecuatoriana Jet Cargo",
    "wof:placetype":"enterprise",
    "wof:subordinate_of":[
        1159288907
    ]
},
  "geometry": {"coordinates":[-78.322784,-1.241567],"type":"Point"}
}