{
  "type": "Feature",
  "properties": {
    "iso:country": "LA",
    "sfomuseum:is_sfo": 1,
    "sfomuseum:placetype": "company",
    "wof:brand_name": "Air Laos",
    "wof:name": "Air Laos",
    "wof:placetype": "enterprise"
  },
  "geometry": {"coordinates":[102.560667,19.43535],"type":"Point"}
}
