{
  "type": "Feature",
  "properties": {
    "date:inception_lower": "2005-01-01",
    "date:inception_upper": "2005-12-31",
    "iso:country": "BA",
    "sfomuseum:is_sfo": 1,
    "sfomuseum:placetype": "company",
    "wd:airline_hub": [
      "Q740392"
    ],
    "wd:country": "Q225",
    "wd:headquarters": "Q11194",
    "wd:instance_of": [
      "Q46970"
    ],
    "wof:brand_name": "Bosna Air",
    "wof:name": "Bosna Air",
    "wof:placetype": "custom",
    "wof:placetype_alt": "company"
  },
  "geometry": {"coordinates":[18.06843,44.091039],"type":"Point"}
}
