{
  "type": "Feature",
  "properties": {
    "date:inception_lower": "1973-01-01",
    "date:inception_upper": "1973-12-31",
    "iso:country": "MT",
    "millsfield:count_images": 4,
    "millsfield:count_objects": 2,
    "sfomuseum:is_sfo": 1,
    "sfomuseum:placetype": "company",
    "wd:airline_hub": [
      "Q672289"
    ],
    "wd:country": "Q233",
    "wd:headquarters": "Q233",
    "wd:instance_of": [
      "Q46970"
    ],
    "wof:brand_name": "Air Malta",
    "wof:name": "Air Malta",
    "wof:placetype": "custom",
    "wof:placetype_alt": "company"
  },
  "geometry": {"coordinates":[14.431432,35.888972],"type":"Point"}
}
