{
  "type": "Feature",
  "properties": {
    "date:inception_lower":"1935-01-01",
    "date:inception_upper":"1935-12-31",
    "iso:country":"US",
    "sfomuseum:is_sfo":1,
    "sfomuseum:placetype":"company",
    "wd:country":"Q30",
    "wd:headquarters":"Q51693",
    "wd:instance_of":[
        "Q4830453",
        "Q6881511"
    ],
    "wof:brand_name":"Taylorcraft",
    "wof:name":"Taylorcraft",
    "wof:placetype":"enterprise"
},
  "geometry": {"coordinates":[-97.470316,25.924894],"type":"Point"}
}