{
  "type": "Feature",
  "properties": {
    "date:inception_lower": "1974-01-01",
    "date:inception_upper": "1974-12-31",
    "flysfo:airline_code": "BA",
    "flysfo:is_sfo": 1,
    "iso:country": "GB",
    "millsfield:count_images": 594,
    "millsfield:count_objects": 393,
    "sfomuseum:count_objects_public": 139,
    "sfomuseum:is_sfo": 1,
    "sfomuseum:label": "British Airways",
    "sfomuseum:name": "British Airways",
    "sfomuseum:placetype": "airline",
    "wd:airline_hub": [
      "Q8691",
      "Q8703"
    ],
    "wd:country": "Q145",
    "wd:headquarters": "Q6552450",
    "wd:instance_of": [
      "Q46970",
      "Q5225895"
    ],
    "wof:name": "British Airways",
    "wof:placetype": "custom",
    "wof:placetype_alt": [
      "airline"
    ],
    "wof:subordinate_of": [
      1159287729
    ]
  },
  "geometry": {"coordinates":[-1.247349,52.418788],"type":"Point"}
}
