{
  "type": "Feature",
  "properties": {
    "iso:country":"LY",
    "sfomuseum:is_sfo":1,
    "sfomuseum:label":"Jamahiriya Air Transport",
    "sfomuseum:name":"Jamahiriya Air Transport",
    "sfomuseum:placetype":"airline",
    "wof:name":"Jamahiriya Air Transport",
    "wof:placetype":"enterprise",
    "wof:subordinate_of":[
        1159288549
    ]
},
  "geometry": {"coordinates":[18.030248,26.666955],"type":"Point"}
}