{
  "type": "Feature",
  "properties": {
    "date:inception_lower": "1921-01-01",
    "date:inception_upper": "1921-12-31",
    "iso:country": "MX",
    "sfomuseum:is_sfo": 1,
    "sfomuseum:placetype": "company",
    "wd:airline_hub": [
      "Q860559",
      "Q932025",
      "Q641967"
    ],
    "wd:country": "Q96",
    "wd:headquarters": "Q1489",
    "wd:instance_of": [
      "Q46970"
    ],
    "wof:brand_name": "Mexican Aviation Company",
    "wof:name": "Mexican Aviation Company",
    "wof:placetype": "custom",
    "wof:placetype_alt": [
      "company"
    ]
  },
  "geometry": {"coordinates":[-102.289691,23.920061],"type":"Point"}
}
