{
  "type": "Feature",
  "properties": {
    "date:inception_lower":"1927-01-01",
    "date:inception_upper":"1927-12-31",
    "iso:country":"US",
    "sfomuseum:is_sfo":1,
    "sfomuseum:label":"Northern Consolidated Airlines",
    "sfomuseum:name":"Northern Consolidated Airlines",
    "sfomuseum:placetype":"airline",
    "wd:airline_hub":[
        "Q767753"
    ],
    "wd:country":"Q30",
    "wd:instance_of":[
        "Q46970"
    ],
    "wof:name":"Northern Consolidated Airlines",
    "wof:placetype":"enterprise",
    "wof:subordinate_of":[
        1159286971
    ]
},
  "geometry": {"coordinates":[-96.999668,39.715956],"type":"Point"}
}