{
  "type": "Feature",
  "properties": {
    "date:inception_lower": "1994-01-01",
    "date:inception_upper": "1994-12-31",
    "iso:country": "MO",
    "millsfield:count_images": 4,
    "millsfield:count_objects": 3,
    "sfomuseum:count_objects_public": 0,
    "sfomuseum:country": "Macau",
    "sfomuseum:is_sfo": 1,
    "sfomuseum:label": "Air Macau",
    "sfomuseum:name": "Air Macau",
    "sfomuseum:placetype": "airline",
    "wd:airline_hub": [
      "Q525486"
    ],
    "wd:country": "Q148",
    "wd:headquarters": "Q14773",
    "wd:instance_of": [
      "Q46970"
    ],
    "wof:name": "Air Macau",
    "wof:placetype": "custom",
    "wof:placetype_alt": "airline",
    "wof:subordinate_of": [
      1159288547
    ]
  },
  "geometry": {"coordinates":[113.54611,22.20056],"type":"Point"}
}
