{
  "type": "Feature",
  "properties": {
    "date:inception_lower": "1946-01-01",
    "date:inception_upper": "1946-12-31",
    "iso:country": "FR",
    "sfomuseum:count_objects_public": 0,
    "sfomuseum:country": "France",
    "sfomuseum:is_sfo": 1,
    "sfomuseum:label": "Aigle Azur",
    "sfomuseum:name": "Aigle Azur",
    "sfomuseum:placetype": "airline",
    "wd:airline_hub": [
      "Q223416"
    ],
    "wd:country": "Q142",
    "wd:headquarters": "Q90",
    "wd:instance_of": [
      "Q46970"
    ],
    "wof:name": "Aigle Azur",
    "wof:placetype": "custom",
    "wof:placetype_alt": "airline",
    "wof:subordinate_of": [
      1159287789
    ]
  },
  "geometry": {"coordinates":[2.342865,48.858705],"type":"Point"}
}
