{
  "type": "Feature",
  "properties": {
    "date:inception_lower":"1919-01-01",
    "date:inception_upper":"1919-12-31",
    "iso:country":"CO",
    "sfomuseum:count_objects_public":0,
    "sfomuseum:is_sfo":1,
    "sfomuseum:label":"SAM Colombia (Sociedad Aeronautica de Medellin)  (Avianca Airlines)",
    "sfomuseum:name":"SAM Colombia (Sociedad Aeronautica de Medellin)",
    "sfomuseum:placetype":"airline",
    "wof:name":"SAM Colombia (Sociedad Aeronautica de Medellin)",
    "wof:placetype":"enterprise",
    "wof:subordinate_of":[
        1159287217
    ]
},
  "geometry": {"coordinates":[-74.08768000000001,4.635456],"type":"Point"}
}