{
  "type": "Feature",
  "properties": {
    "date:inception_lower": "1971-01-01",
    "date:inception_upper": "1971-12-31",
    "iso:country": "CR",
    "millsfield:count_images": 2,
    "millsfield:count_objects": 2,
    "sfomuseum:count_objects_public": 1,
    "sfomuseum:country": "Brasil",
    "sfomuseum:is_sfo": 1,
    "sfomuseum:label": "Austral Airlines",
    "sfomuseum:name": "Austral Airlines",
    "sfomuseum:placetype": "airline",
    "wof:name": "Austral Airlines",
    "wof:placetype": "custom",
    "wof:placetype_alt": [
      "airline"
    ],
    "wof:subordinate_of": [
      1159288747
    ]
  },
  "geometry": {"coordinates":[-84.028584,10.068183],"type":"Point"}
}
