{
  "type": "Feature",
  "properties": {
    "iso:country":"FR",
    "sfomuseum:count_objects_public":0,
    "sfomuseum:is_sfo":1,
    "sfomuseum:label":"TAI (Transportes Aeriens Intercontinentaux)",
    "sfomuseum:name":"TAI (Transportes Aeriens Intercontinentaux)",
    "sfomuseum:placetype":"airline",
    "wof:name":"TAI (Transportes Aeriens Intercontinentaux)",
    "wof:placetype":"enterprise",
    "wof:subordinate_of":[
        1159287115
    ]
},
  "geometry": {"coordinates":[2.549047,46.698481],"type":"Point"}
}