{
  "type": "Feature",
  "properties": {
    "date:inception_lower": "1945-01-01",
    "date:inception_upper": "1945-12-31",
    "flysfo:airline_code": "TP",
    "flysfo:is_sfo": 1,
    "millsfield:count_images": 51,
    "millsfield:count_objects": 25,
    "sfomuseum:count_objects_public": 1,
    "sfomuseum:is_sfo": 1,
    "sfomuseum:label": "TAP Air Portugal",
    "sfomuseum:name": "TAP Air Portugal",
    "sfomuseum:placetype": "airline",
    "wd:airline_hub": [
      "Q403671",
      "Q943743",
      "Q639161"
    ],
    "wd:country": "Q45",
    "wd:headquarters": "Q403671",
    "wd:instance_of": [
      "Q46970"
    ],
    "wof:name": "TAP Air Portugal",
    "wof:placetype": "custom",
    "wof:placetype_alt": "airline",
    "wof:subordinate_of": [
      1159287519
    ]
  },
  "geometry": {"coordinates":[-9.135591,38.772844],"type":"Point"}
}
