{
  "type": "Feature",
  "properties": {
    "date:inception_lower": "1991-01-01",
    "date:inception_upper": "1991-12-31",
    "iso:country": "NL",
    "sfomuseum:count_objects_public": 0,
    "sfomuseum:is_sfo": 1,
    "sfomuseum:label": "KLM cityhopper  (KLM (Royal Dutch Airlines))",
    "sfomuseum:name": "KLM cityhopper",
    "sfomuseum:placetype": "airline",
    "wd:airline_hub": [
      "Q9694"
    ],
    "wd:country": "Q55",
    "wd:headquarters": "Q9924",
    "wd:instance_of": [
      "Q46970"
    ],
    "wof:name": "KLM cityhopper",
    "wof:placetype": "custom",
    "wof:placetype_alt": "airline",
    "wof:subordinate_of": [
      1159287541
    ]
  },
  "geometry": {"coordinates":[5.501896,52.554205],"type":"Point"}
}
