{
  "type": "Feature",
  "properties": {
    "date:inception_lower": "1941-01-01",
    "date:inception_upper": "1941-12-31",
    "iso:country": "PH",
    "millsfield:count_images": 33,
    "millsfield:count_objects": 37,
    "sfomuseum:count_objects_public": 28,
    "sfomuseum:is_sfo": 1,
    "sfomuseum:label": "Philippine Airlines",
    "sfomuseum:name": "Philippine Airlines",
    "sfomuseum:placetype": "airline",
    "wd:airline_hub": [
      "Q86446",
      "Q1048704"
    ],
    "wd:country": "Q928",
    "wd:headquarters": "Q17189",
    "wd:instance_of": [
      "Q46970"
    ],
    "wof:name": "Philippine Airlines",
    "wof:placetype": "custom",
    "wof:placetype_alt": "airline",
    "wof:subordinate_of": [
      1159287151
    ]
  },
  "geometry": {"coordinates":[120.99694,14.54806],"type":"Point"}
}
