{
  "type": "Feature",
  "properties": {
    "date:inception_lower":"1987-01-01",
    "date:inception_upper":"1987-12-31",
    "iso:country":"FR",
    "name:unk_x_preferred":[
        "Air Libert\u00e9"
    ],
    "sfomuseum:is_sfo":1,
    "sfomuseum:placetype":"company",
    "wd:country":"Q142",
    "wd:headquarters":"Q478105",
    "wd:instance_of":[
        "Q46970"
    ],
    "wof:brand_name":"Air Liberte",
    "wof:name":"Air Liberte",
    "wof:placetype":"enterprise"
},
  "geometry": {"coordinates":[2.352789,48.749185],"type":"Point"}
}