{
  "type": "Feature",
  "properties": {
    "date:inception_lower": "2003-01-01",
    "date:inception_upper": "2003-12-31",
    "iso:country": "AU",
    "sfomuseum:count_objects_public": 3,
    "sfomuseum:is_sfo": 1,
    "sfomuseum:label": "Jetstar Airways",
    "sfomuseum:name": "Jetstar Airways",
    "sfomuseum:placetype": "airline",
    "wd:airline_hub": [
      "Q733738",
      "Q45523",
      "Q1175431",
      "Q474632"
    ],
    "wd:country": "Q408",
    "wd:headquarters": "Q3141",
    "wd:instance_of": [
      "Q46970"
    ],
    "wof:name": "Jetstar Airways",
    "wof:placetype": "enterprise",
    "wof:subordinate_of": [
      1159288015
    ]
  },
  "geometry": {"coordinates":[144.978682,-37.825071],"type":"Point"}
}
