{
  "type": "Feature",
  "properties": {
    "date:inception_lower": "1944-01-01",
    "date:inception_upper": "1944-12-31",
    "iso:country": "IS",
    "millsfield:count_images": 26,
    "millsfield:count_objects": 18,
    "name:unk_x_preferred": [
      "Loftleiðir HF"
    ],
    "sfomuseum:is_sfo": 1,
    "sfomuseum:placetype": "company",
    "wd:country": "Q189",
    "wd:instance_of": [
      "Q46970"
    ],
    "wof:brand_name": "Loftleidir HF",
    "wof:name": "Loftleidir HF",
    "wof:placetype": "custom",
    "wof:placetype_alt": "company"
  },
  "geometry": {"coordinates":[-18.673522,64.779262],"type":"Point"}
}
