{
  "type": "Feature",
  "properties": {
    "iso:country": "BS",
    "millsfield:count_images": 3,
    "millsfield:count_objects": 3,
    "sfomuseum:count_objects_public": 1,
    "sfomuseum:is_sfo": 1,
    "sfomuseum:label": "Bahamas Airways",
    "sfomuseum:name": "Bahamas Airways",
    "sfomuseum:placetype": "airline",
    "wof:name": "Bahamas Airways",
    "wof:placetype": "custom",
    "wof:placetype_alt": "airline",
    "wof:subordinate_of": [
      1159287825
    ]
  },
  "geometry": {"coordinates":[-78.018505,24.669637],"type":"Point"}
}
