{
  "type": "Feature",
  "properties": {
    "date:inception_lower": "1965-01-01",
    "date:inception_upper": "1965-12-31",
    "iso:country": "LY",
    "millsfield:count_images": 2,
    "millsfield:count_objects": 1,
    "sfomuseum:is_sfo": 1,
    "sfomuseum:placetype": "company",
    "wd:airline_hub": [
      "Q44588"
    ],
    "wd:country": "Q1016",
    "wd:headquarters": "Q3579",
    "wd:instance_of": [
      "Q46970"
    ],
    "wof:brand_name": "Libyan Arab Airlines",
    "wof:name": "Libyan Arab Airlines",
    "wof:placetype": "custom",
    "wof:placetype_alt": "company"
  },
  "geometry": {"coordinates":[18.030248,26.666955],"type":"Point"}
}
