{
  "type": "Feature",
  "properties": {
    "iso:country": "FR",
    "sfomuseum:is_sfo": 1,
    "sfomuseum:placetype": "company",
    "wd:instance_of": [
      "Q43229"
    ],
    "wof:brand_name": "Air Provence",
    "wof:name": "Air Provence",
    "wof:placetype": "custom",
    "wof:placetype_alt": "company"
  },
  "geometry": {"coordinates":[2.549047,46.698481],"type":"Point"}
}
