{
  "type": "Feature",
  "properties": {
    "date:inception_lower": "1929-01-01",
    "date:inception_upper": "1929-12-31",
    "iso:country": "CU",
    "millsfield:count_images": 7,
    "millsfield:count_objects": 6,
    "sfomuseum:count_objects_public": 6,
    "sfomuseum:is_sfo": 1,
    "sfomuseum:label": "Cubana de Aviaci贸n S.A.  (Cubana Airlines)",
    "sfomuseum:name": "Cubana de Aviaci贸n S.A.",
    "sfomuseum:placetype": "airline",
    "wd:airline_hub": [
      "Q381677"
    ],
    "wd:country": "Q241",
    "wd:headquarters": "Q1563",
    "wd:instance_of": [
      "Q46970"
    ],
    "wof:name": "Cubana de Aviaci贸n S.A.",
    "wof:placetype": "custom",
    "wof:placetype_alt": "airline",
    "wof:subordinate_of": [
      1159288275
    ]
  },
  "geometry": {"coordinates":[-82.38304,23.13302],"type":"Point"}
}
