{
  "type": "Feature",
  "properties": {
    "date:inception_lower": "1978-01-01",
    "date:inception_upper": "1978-12-31",
    "iso:country": "JP",
    "sfomuseum:count_objects_public": 17,
    "sfomuseum:is_sfo": 1,
    "sfomuseum:label": "Nippon Cargo Airlines",
    "sfomuseum:name": "Nippon Cargo Airlines",
    "sfomuseum:placetype": "airline",
    "wd:airline_hub": [
      "Q36454",
      "Q193682",
      "Q1197455"
    ],
    "wd:country": "Q17",
    "wd:headquarters": "Q36454",
    "wd:instance_of": [
      "Q46970"
    ],
    "wof:name": "Nippon Cargo Airlines",
    "wof:placetype": "custom",
    "wof:placetype_alt": "airline",
    "wof:subordinate_of": [
      1159287387
    ]
  },
  "geometry": {"coordinates":[140.395257,35.755744],"type":"Point"}
}
