{
  "type": "Feature",
  "properties": {
    "date:inception_lower": "1948-01-01",
    "date:inception_upper": "1948-12-31",
    "iso:country": "US",
    "sfomuseum:count_objects_public": 0,
    "sfomuseum:is_sfo": 1,
    "sfomuseum:placetype": "company",
    "wd:country": "Q30",
    "wd:instance_of": [
      "Q936518"
    ],
    "wof:brand_name": "Helio",
    "wof:name": "Helio",
    "wof:placetype": "custom",
    "wof:placetype_alt": "company"
  },
  "geometry": {"coordinates":[-96.999668,39.715956],"type":"Point"}
}
