{
  "type": "Feature",
  "properties": {
    "iso:country": "AU",
    "sfomuseum:count_objects_public": 0,
    "sfomuseum:is_sfo": 1,
    "sfomuseum:label": "Woods Airways",
    "sfomuseum:name": "Woods Airways",
    "sfomuseum:placetype": "airline",
    "wof:name": "Woods Airways",
    "wof:placetype": "custom",
    "wof:placetype_alt": "airline",
    "wof:subordinate_of": [
      1159287121
    ]
  },
  "geometry": {"coordinates":[134.050443,-23.992438],"type":"Point"}
}
