{
  "type": "Feature",
  "properties": {
    "date:inception_lower": "1955-01-01",
    "date:inception_upper": "1955-12-31",
    "iso:country": "PK",
    "sfomuseum:count_objects_public": 0,
    "sfomuseum:is_sfo": 1,
    "sfomuseum:label": "Pakistan International Cargo  (Pakistan International Airlines)",
    "sfomuseum:name": "Pakistan International Cargo",
    "sfomuseum:placetype": "airline",
    "wof:name": "Pakistan International Cargo",
    "wof:placetype": "enterprise",
    "wof:subordinate_of": [
      1159288213
    ]
  },
  "geometry": {"coordinates":[68.560265,29.329836],"type":"Point"}
}
