{
  "type": "Feature",
  "properties": {
    "date:inception_lower": "1913-01-01",
    "date:inception_upper": "1913-12-31",
    "iso:country": "DE",
    "sfomuseum:count_objects_public": 1,
    "sfomuseum:is_sfo": 1,
    "sfomuseum:placetype": "company",
    "wd:country": "Q1206012",
    "wd:headquarters": "Q6829",
    "wd:instance_of": [
      "Q936518"
    ],
    "wof:brand_name": "Pfalz",
    "wof:name": "Pfalz",
    "wof:placetype": "custom",
    "wof:placetype_alt": "company"
  },
  "geometry": {"coordinates":[8.437615,49.319469],"type":"Point"}
}
