{
  "type": "Feature",
  "properties": {
    "date:inception_lower": "1928-01-01",
    "date:inception_upper": "1928-12-31",
    "iso:country": "US",
    "sfomuseum:count_objects_public": 2,
    "sfomuseum:is_sfo": 1,
    "sfomuseum:label": "Transcontinental Air Transport (TAT)",
    "sfomuseum:name": "Transcontinental Air Transport (TAT)",
    "sfomuseum:placetype": "airline",
    "wof:name": "Transcontinental Air Transport (TAT)",
    "wof:placetype": "enterprise",
    "wof:subordinate_of": [
      1159287811
    ]
  },
  "geometry": {"coordinates":[-96.999668,39.715956],"type":"Point"}
}
