{
  "type": "Feature",
  "properties": {
    "iso:country":"NO",
    "sfomuseum:brand":"DNL Norwegian Air Lines ",
    "sfomuseum:count_objects_public":0,
    "sfomuseum:is_sfo":1,
    "sfomuseum:label":"DNL Norwegian Air Lines  (DNL Norwegian Air Lines )",
    "sfomuseum:name":"DNL Norwegian Air Lines",
    "sfomuseum:placetype":"airline",
    "wof:name":"DNL Norwegian Air Lines",
    "wof:placetype":"enterprise",
    "wof:subordinate_of":[
        1159287641
    ]
},
  "geometry": {"coordinates":[9.680372,61.356908],"type":"Point"}
}