{
  "type": "Feature",
  "properties": {
    "date:inception_lower": "1990-01-01",
    "date:inception_upper": "1990-12-31",
    "iso:country": "RU",
    "millsfield:count_objects": 1,
    "sfomuseum:is_sfo": 1,
    "sfomuseum:placetype": "company",
    "wd:airline_hub": [
      "Q2545194"
    ],
    "wd:country": "Q159",
    "wd:headquarters": "Q5627",
    "wd:instance_of": [
      "Q46970"
    ],
    "wof:brand_name": "Volga-Dnepr Airlines",
    "wof:name": "Volga-Dnepr Airlines",
    "wof:placetype": "custom",
    "wof:placetype_alt": "company"
  },
  "geometry": {"coordinates":[48.298334,54.303602],"type":"Point"}
}
