{
  "type": "Feature",
  "properties": {
    "date:inception_lower":"1988-01-01",
    "date:inception_upper":"1988-12-31",
    "flysfo:airline_code":"HX",
    "flysfo:is_sfo":1,
    "iso:country":"DE",
    "sfomuseum:is_sfo":1,
    "sfomuseum:label":"Hamburg Airlines",
    "sfomuseum:name":"Hamburg Airlines",
    "sfomuseum:placetype":"airline",
    "wd:airline_hub":[
        "Q27706"
    ],
    "wd:country":"Q183",
    "wd:headquarters":"Q1055",
    "wd:instance_of":[
        "Q46970"
    ],
    "wof:name":"Hamburg Airlines",
    "wof:placetype":"enterprise",
    "wof:subordinate_of":[
        1159286835
    ]
},
  "geometry": {"coordinates":[9.62743,51.196755],"type":"Point"}
}