{
  "type": "Feature",
  "properties": {
    "date:inception_lower": "1997-01-01",
    "date:inception_upper": "1997-12-31",
    "iso:country": "EG",
    "millsfield:count_images": 1,
    "millsfield:count_objects": 1,
    "sfomuseum:is_sfo": 1,
    "sfomuseum:placetype": "company",
    "wd:airline_hub": [
      "Q461793"
    ],
    "wd:country": "Q79",
    "wd:headquarters": "Q85",
    "wd:instance_of": [
      "Q46970"
    ],
    "wof:brand_name": "Lotus Airways",
    "wof:name": "Lotus Airways",
    "wof:placetype": "custom",
    "wof:placetype_alt": "company"
  },
  "geometry": {"coordinates":[29.227089,26.42231],"type":"Point"}
}
