{
  "type": "Feature",
  "properties": {
    "iso:country": "EC",
    "sfomuseum:count_objects_public": 0,
    "sfomuseum:is_sfo": 1,
    "sfomuseum:label": "AECA Carga",
    "sfomuseum:name": "AECA Carga",
    "sfomuseum:placetype": "airline",
    "wof:name": "AECA Carga",
    "wof:placetype": "enterprise",
    "wof:subordinate_of": [
      1159287787
    ]
  },
  "geometry": {"coordinates":[-78.322784,-1.241567],"type":"Point"}
}
