{
  "type": "Feature",
  "properties": {
    "date:inception_lower": "1957-01-01",
    "date:inception_upper": "1957-12-31",
    "iso:country": "TW",
    "millsfield:count_images": 19,
    "millsfield:count_objects": 11,
    "sfomuseum:is_sfo": 1,
    "sfomuseum:placetype": "company",
    "wd:airline_hub": [
      "Q702019"
    ],
    "wd:country": "Q865",
    "wd:instance_of": [
      "Q46970"
    ],
    "wof:brand_name": "Far Eastern Air Transport Corporation (FAT)",
    "wof:name": "Far Eastern Air Transport Corporation (FAT)",
    "wof:placetype": "custom",
    "wof:placetype_alt": "company"
  },
  "geometry": {"coordinates":[120.955426,23.798532],"type":"Point"}
}
