{
  "type": "Feature",
  "properties": {
    "date:inception_lower":"1946-01-01",
    "date:inception_upper":"1946-12-31",
    "flysfo:airline_code":"SK",
    "flysfo:is_sfo":1,
    "iso:country":"SE",
    "sfomuseum:is_sfo":1,
    "sfomuseum:label":"Scandinavian Airlines System (SAS)",
    "sfomuseum:name":"Scandinavian Airlines System (SAS)",
    "sfomuseum:placetype":"airline",
    "wd:airline_hub":[
        "Q206277",
        "Q210559",
        "Q223499"
    ],
    "wd:country":"Q34",
    "wd:headquarters":"Q10673294",
    "wd:instance_of":[
        "Q46970"
    ],
    "wof:name":"Scandinavian Airlines System (SAS)",
    "wof:placetype":"enterprise",
    "wof:subordinate_of":[
        1159287667
    ]
},
  "geometry": {"coordinates":[19.017205,65.859144],"type":"Point"}
}