{
  "type": "Feature",
  "properties": {
    "date:inception_lower":"1978-01-01",
    "date:inception_upper":"1978-12-31",
    "iso:country":"GB",
    "sfomuseum:is_sfo":1,
    "sfomuseum:placetype":"company",
    "wd:airline_hub":[
        "Q8703"
    ],
    "wd:country":"Q145",
    "wd:instance_of":[
        "Q46970"
    ],
    "wof:brand_name":"Air Europe",
    "wof:name":"Air Europe",
    "wof:placetype":"enterprise"
},
  "geometry": {"coordinates":[-1.247349,52.418788],"type":"Point"}
}