{
  "type": "Feature",
  "properties": {
    "date:inception_lower": "1919-01-01",
    "date:inception_upper": "1919-12-31",
    "iso:country": "CO",
    "millsfield:count_images": 7,
    "millsfield:count_objects": 7,
    "sfomuseum:brand": "SCADTA (Sociedad Colombo Alemana de Transporte Aéreo)",
    "sfomuseum:count_objects_public": 7,
    "sfomuseum:is_sfo": 1,
    "sfomuseum:label": "SCADTA (Sociedad Colombo Alemana de Transporte Aéreo)",
    "sfomuseum:name": "SCADTA (Sociedad Colombo Alemana de Transporte Aéreo)",
    "sfomuseum:placetype": "airline",
    "wof:name": "SCADTA (Sociedad Colombo Alemana de Transporte Aéreo)",
    "wof:placetype": "custom",
    "wof:placetype_alt": "airline",
    "wof:subordinate_of": [
      1159286991
    ]
  },
  "geometry": {"coordinates":[-73.166783,3.420497],"type":"Point"}
}
