{
  "type": "Feature",
  "properties": {
    "date:inception_lower":"1952-01-01",
    "date:inception_upper":"1952-12-31",
    "iso:country":"CA",
    "sfomuseum:is_sfo":1,
    "sfomuseum:placetype":"company",
    "wd:airline_hub":[
        "Q269588"
    ],
    "wd:country":"Q16",
    "wd:instance_of":[
        "Q46970"
    ],
    "wof:brand_name":"Wardair",
    "wof:name":"Wardair",
    "wof:placetype":"enterprise"
},
  "geometry": {"coordinates":[-112.38485799999999,58.33747],"type":"Point"}
}