{
  "type": "Feature",
  "properties": {
    "date:inception_lower":"2003-01-01",
    "date:inception_upper":"2003-12-31",
    "iso:country":"SG",
    "sfomuseum:is_sfo":1,
    "sfomuseum:placetype":"company",
    "wd:airline_hub":[
        "Q32159"
    ],
    "wd:country":"Q334",
    "wd:headquarters":"Q334",
    "wd:instance_of":[
        "Q46970",
        "Q190915"
    ],
    "wof:brand_name":"TigerAir",
    "wof:name":"TigerAir",
    "wof:placetype":"enterprise"
},
  "geometry": {"coordinates":[103.80938,1.357685],"type":"Point"}
}