{
  "type": "Feature",
  "properties": {
    "date:inception_lower": "1946-01-01",
    "date:inception_upper": "1946-12-31",
    "iso:country": "CA",
    "millsfield:count_images": 37,
    "millsfield:count_objects": 27,
    "sfomuseum:is_sfo": 1,
    "sfomuseum:placetype": "company",
    "wd:country": "Q16",
    "wd:instance_of": [
      "Q46970"
    ],
    "wof:brand_name": "Pacific Western Airlines (PWA)",
    "wof:name": "Pacific Western Airlines (PWA)",
    "wof:placetype": "custom",
    "wof:placetype_alt": "company"
  },
  "geometry": {"coordinates":[-112.384858,58.33747],"type":"Point"}
}
