{
  "type": "Feature",
  "properties": {
    "date:inception_lower": "1942-01-01",
    "date:inception_upper": "1942-12-31",
    "iso:country": "CA",
    "millsfield:count_images": 1,
    "millsfield:count_objects": 2,
    "sfomuseum:count_objects_public": 0,
    "sfomuseum:is_sfo": 1,
    "sfomuseum:placetype": "company",
    "wd:country": "Q321529",
    "wd:headquarters": "Q340",
    "wd:instance_of": [
      "Q891723",
      "Q936518"
    ],
    "wof:brand_name": "Bombardier",
    "wof:name": "Bombardier",
    "wof:placetype": "custom",
    "wof:placetype_alt": "company"
  },
  "geometry": {"coordinates":[-73.587778,45.508889],"type":"Point"}
}
