{
  "type": "Feature",
  "properties": {
    "iso:country": "DO",
    "sfomuseum:count_objects_public": 0,
    "sfomuseum:is_sfo": 1,
    "sfomuseum:label": "Aerotours Dominicano Airlines",
    "sfomuseum:name": "Aerotours Dominicano Airlines",
    "sfomuseum:placetype": "airline",
    "wof:name": "Aerotours Dominicano Airlines",
    "wof:placetype": "enterprise",
    "wof:subordinate_of": [
      1159286747
    ]
  },
  "geometry": {"coordinates":[-70.804224,19.105937],"type":"Point"}
}
