{
  "type": "Feature",
  "properties": {
    "date:inception_lower": "1929-01-01",
    "date:inception_upper": "1929-12-31",
    "flysfo:airline_code": "LA",
    "flysfo:is_sfo": 1,
    "iso:country": "CL",
    "millsfield:count_images": 5,
    "millsfield:count_objects": 5,
    "sfomuseum:is_sfo": 1,
    "sfomuseum:placetype": "company",
    "wd:airline_hub": [
      "Q127671",
      "Q1142219"
    ],
    "wd:country": "Q298",
    "wd:headquarters": "Q14484",
    "wd:instance_of": [
      "Q46970"
    ],
    "wof:brand_name": "LAN Airlines",
    "wof:name": "LAN Airlines",
    "wof:placetype": "custom",
    "wof:placetype_alt": [
      "company"
    ]
  },
  "geometry": {"coordinates":[-72.288079,-38.165295],"type":"Point"}
}
