{
  "type": "Feature",
  "properties": {
    "date:inception_lower": "2005-01-01",
    "date:inception_upper": "2005-12-31",
    "iso:country": "MX",
    "millsfield:count_images": 1,
    "millsfield:count_objects": 2,
    "sfomuseum:is_sfo": 1,
    "sfomuseum:placetype": "company",
    "wd:airline_hub": [
      "Q860559"
    ],
    "wd:country": "Q96",
    "wd:headquarters": "Q1489",
    "wd:instance_of": [
      "Q46970"
    ],
    "wof:brand_name": "Interjet",
    "wof:name": "Interjet",
    "wof:placetype": "custom",
    "wof:placetype_alt": "company"
  },
  "geometry": {"coordinates":[-99.150344,19.371422],"type":"Point"}
}
