{
  "type": "Feature",
  "properties": {
    "date:inception_lower": "1999-01-01",
    "date:inception_upper": "1999-12-31",
    "iso:country": "AE",
    "millsfield:count_images": 1,
    "millsfield:count_objects": 1,
    "sfomuseum:count_objects_public": 0,
    "sfomuseum:is_sfo": 1,
    "sfomuseum:label": "Aria Air Tour",
    "sfomuseum:name": "Aria Air Tour",
    "sfomuseum:placetype": "airline",
    "wof:name": "Aria Air Tour",
    "wof:placetype": "custom",
    "wof:placetype_alt": "airline",
    "wof:subordinate_of": [
      1159286543
    ]
  },
  "geometry": {"coordinates":[54.576046,23.47438],"type":"Point"}
}
