{
  "type": "Feature",
  "properties": {
    "date:inception_lower":"1945-01-01",
    "date:inception_upper":"1945-12-31",
    "iso:country":"KE",
    "sfomuseum:is_sfo":1,
    "sfomuseum:label":"East African Airways",
    "sfomuseum:name":"East African Airways",
    "sfomuseum:placetype":"airline",
    "wd:airline_hub":[
        "Q206349"
    ],
    "wd:country":"Q114",
    "wd:instance_of":[
        "Q46970"
    ],
    "wof:name":"East African Airways",
    "wof:placetype":"enterprise",
    "wof:subordinate_of":[
        1159287365
    ]
},
  "geometry": {"coordinates":[37.918308,0.543716],"type":"Point"}
}