{
  "type": "Feature",
  "properties": {
    "date:cessation_lower": "1990-01-01",
    "date:cessation_upper": "1990-12-31",
    "date:inception_lower": "1980-01-01",
    "date:inception_upper": "1980-12-31",
    "sfomuseum:count_objects_public": 0,
    "sfomuseum:country": "Panama",
    "sfomuseum:hub": "Tocumen International Airport",
    "sfomuseum:is_sfo": 1,
    "sfomuseum:label": "Air Panama  (Air Panama Internacional)",
    "sfomuseum:name": "Air Panama",
    "sfomuseum:placetype": "airline",
    "wd:airline_hub": [
      "Q3496541"
    ],
    "wd:country": "Q804",
    "wd:headquarters": "Q3496541",
    "wd:instance_of": [
      "Q46970"
    ],
    "wof:name": "Air Panama",
    "wof:placetype": "enterprise",
    "wof:subordinate_of": [
      1159287043
    ]
  },
  "geometry": {"coordinates":[-80.338454,8.72491],"type":"Point"}
}
