{
  "type": "Feature",
  "properties": {
    "date:inception_lower":"1936-01-01",
    "date:inception_upper":"1936-12-31",
    "iso:country":"AU",
    "sfomuseum:is_sfo":1,
    "sfomuseum:placetype":"company",
    "wd:country":"Q408",
    "wd:instance_of":[
        "Q46970"
    ],
    "wof:brand_name":"Australian National Airways",
    "wof:name":"Australian National Airways",
    "wof:placetype":"enterprise"
},
  "geometry": {"coordinates":[134.050443,-23.992438],"type":"Point"}
}