{
  "type": "Feature",
  "properties": {
    "date:inception_lower": "1927-01-01",
    "date:inception_upper": "1927-12-31",
    "iso:country": "RS",
    "sfomuseum:count_objects_public": 2,
    "sfomuseum:is_sfo": 1,
    "sfomuseum:label": "Jugoslovenski Aerotransport (JAT)",
    "sfomuseum:name": "Jugoslovenski Aerotransport (JAT)",
    "sfomuseum:placetype": "airline",
    "wof:name": "Jugoslovenski Aerotransport (JAT)",
    "wof:placetype": "custom",
    "wof:placetype_alt": "airline",
    "wof:subordinate_of": [
      1159287401
    ]
  },
  "geometry": {"coordinates":[20.589197,44.251791],"type":"Point"}
}
