{
  "type": "Feature",
  "properties": {
    "date:inception_lower": "1948-01-01",
    "date:inception_upper": "1948-12-31",
    "iso:country": "TN",
    "millsfield:count_objects": 2,
    "sfomuseum:count_objects_public": 2,
    "sfomuseum:is_sfo": 1,
    "sfomuseum:label": "Tunisair",
    "sfomuseum:name": "Tunisair",
    "sfomuseum:placetype": "airline",
    "wd:airline_hub": [
      "Q1141214"
    ],
    "wd:country": "Q948",
    "wd:headquarters": "Q3572",
    "wd:instance_of": [
      "Q46970"
    ],
    "wof:name": "Tunisair",
    "wof:placetype": "custom",
    "wof:placetype_alt": "airline",
    "wof:subordinate_of": [
      1159288553
    ]
  },
  "geometry": {"coordinates":[10.16579,36.81897],"type":"Point"}
}
