{
  "type": "Feature",
  "properties": {
    "iso:country":"CA",
    "sfomuseum:count_objects_public":0,
    "sfomuseum:is_sfo":1,
    "sfomuseum:label":"Northway Aviation",
    "sfomuseum:name":"Northway Aviation",
    "sfomuseum:placetype":"airline",
    "wof:name":"Northway Aviation",
    "wof:placetype":"enterprise",
    "wof:subordinate_of":[
        1159287425
    ]
},
  "geometry": {"coordinates":[-112.38485799999999,58.33747],"type":"Point"}
}