{
  "type": "Feature",
  "properties": {
    "date:inception_lower":"1919-01-01",
    "date:inception_upper":"1919-12-31",
    "iso:country":"CH",
    "sfomuseum:is_sfo":1,
    "sfomuseum:placetype":"company",
    "wd:country":"Q39",
    "wd:headquarters":"Q72",
    "wd:instance_of":[
        "Q46970"
    ],
    "wof:brand_name":"Ad Astra Aero",
    "wof:name":"Ad Astra Aero",
    "wof:placetype":"enterprise"
},
  "geometry": {"coordinates":[8.517105,47.377514],"type":"Point"}
}