{
  "type": "Feature",
  "properties": {
    "date:inception_lower":"2005-01-01",
    "date:inception_upper":"2005-12-31",
    "flysfo:code":"4O",
    "flysfo:is_sfo":1,
    "flysfo:name":"Interjet",
    "iso:country":"MX",
    "sfomuseum:is_sfo":1,
    "sfomuseum:label":"Interjet",
    "sfomuseum:name":"Interjet",
    "sfomuseum:placetype":"airline",
    "wd:airline_hub":[
        "Q860559"
    ],
    "wd:country":"Q96",
    "wd:headquarters":"Q1489",
    "wd:instance_of":[
        "Q46970"
    ],
    "wof:name":"Interjet",
    "wof:placetype":"enterprise",
    "wof:subordinate_of":[
        1159286581
    ]
},
  "geometry": {"coordinates":[-99.150344,19.371422],"type":"Point"}
}