{
  "type": "Feature",
  "properties": {
    "date:inception_lower": "1962-01-01",
    "date:inception_upper": "1962-12-31",
    "iso:country": "ID",
    "millsfield:count_images": 1,
    "millsfield:count_objects": 1,
    "sfomuseum:count_objects_public": 0,
    "sfomuseum:is_sfo": 1,
    "sfomuseum:label": "Merpati Airlines",
    "sfomuseum:name": "Merpati Airlines",
    "sfomuseum:placetype": "airline",
    "wof:name": "Merpati Airlines",
    "wof:placetype": "custom",
    "wof:placetype_alt": "airline",
    "wof:subordinate_of": [
      1159287501
    ]
  },
  "geometry": {"coordinates":[101.972332,-1.003189],"type":"Point"}
}
