{
  "type": "Feature",
  "properties": {
    "date:inception_lower":"1962-01-01",
    "date:inception_upper":"1962-12-31",
    "iso:country":"ID",
    "sfomuseum:is_sfo":1,
    "sfomuseum:label":"Merpati Airlines",
    "sfomuseum:name":"Merpati Airlines",
    "sfomuseum:placetype":"airline",
    "wof:name":"Merpati Airlines",
    "wof:placetype":"enterprise",
    "wof:subordinate_of":[
        1159287501
    ]
},
  "geometry": {"coordinates":[101.97233199999999,-1.003189],"type":"Point"}
}