{
  "type": "Feature",
  "properties": {
    "date:inception_lower": "1912-01-01",
    "date:inception_upper": "1912-12-31",
    "iso:country": "GB",
    "sfomuseum:is_sfo": 1,
    "sfomuseum:placetype": "company",
    "wd:headquarters": "Q890621",
    "wd:instance_of": [
      "Q4830453"
    ],
    "wof:brand_name": "Norman Thompson Flight",
    "wof:name": "Norman Thompson Flight",
    "wof:placetype": "enterprise"
  },
  "geometry": {"coordinates":[-1.247349,52.418788],"type":"Point"}
}
