{
  "type": "Feature",
  "properties": {
    "date:inception_lower":"1956-01-01",
    "date:inception_upper":"1956-12-31",
    "iso:country":"VN",
    "sfomuseum:count_objects_public":3,
    "sfomuseum:is_sfo":1,
    "sfomuseum:label":"Vietnam Airlines",
    "sfomuseum:name":"Vietnam Airlines",
    "sfomuseum:placetype":"airline",
    "wd:airline_hub":[
        "Q844098",
        "Q478595",
        "Q42840",
        "Q773330"
    ],
    "wd:country":"Q881",
    "wd:headquarters":"Q864802",
    "wd:instance_of":[
        "Q46970"
    ],
    "wof:name":"Vietnam Airlines",
    "wof:placetype":"enterprise",
    "wof:subordinate_of":[
        1159286777
    ]
},
  "geometry": {"coordinates":[105.89814699999999,21.044737],"type":"Point"}
}