{
  "type": "Feature",
  "properties": {
    "iso:country":"MX",
    "name:unk_x_preferred":[
        "LAMSA (L\u00edneas A\u00e9reas Mexicanas)"
    ],
    "sfomuseum:is_sfo":1,
    "sfomuseum:placetype":"company",
    "wof:brand_name":"LAMSA (Lineas Aereas Mexicanas)",
    "wof:name":"LAMSA (Lineas Aereas Mexicanas)",
    "wof:placetype":"enterprise"
},
  "geometry": {"coordinates":[-102.289691,23.920061],"type":"Point"}
}