{
  "type": "Feature",
  "properties": {
    "iso:country": "MX",
    "millsfield:count_images": 7,
    "millsfield:count_objects": 7,
    "name:unk_x_preferred": [
      "LAMSA (Líneas Aéreas Mexicanas)"
    ],
    "sfomuseum:is_sfo": 1,
    "sfomuseum:placetype": "company",
    "wof:brand_name": "LAMSA (Lineas Aereas Mexicanas)",
    "wof:name": "LAMSA (Lineas Aereas Mexicanas)",
    "wof:placetype": "custom",
    "wof:placetype_alt": [
      "company"
    ]
  },
  "geometry": {"coordinates":[-102.289691,23.920061],"type":"Point"}
}
