{
  "type": "Feature",
  "properties": {
    "date:inception_lower": "1946-01-01",
    "date:inception_upper": "1946-12-31",
    "iso:country": "AU",
    "millsfield:count_images": 45,
    "millsfield:count_objects": 40,
    "sfomuseum:is_sfo": 1,
    "sfomuseum:placetype": "company",
    "wd:airline_hub": [
      "Q733738"
    ],
    "wd:country": "Q408",
    "wd:instance_of": [
      "Q46970"
    ],
    "wof:brand_name": "Trans Australia Airlines (TAA)",
    "wof:name": "Trans Australia Airlines (TAA)",
    "wof:placetype": "custom",
    "wof:placetype_alt": "company"
  },
  "geometry": {"coordinates":[134.050443,-23.992438],"type":"Point"}
}
