{
  "type": "Feature",
  "properties": {
    "date:inception_lower": "1932-01-01",
    "date:inception_upper": "1932-12-31",
    "iso:country": "US",
    "millsfield:count_images": 7,
    "millsfield:count_objects": 5,
    "sfomuseum:count_objects_public": 5,
    "sfomuseum:is_sfo": 1,
    "sfomuseum:label": "Pacific Alaska Airways",
    "sfomuseum:name": "Pacific Alaska Airways",
    "sfomuseum:placetype": "airline",
    "wd:instance_of": [
      "Q46970"
    ],
    "wof:name": "Pacific Alaska Airways",
    "wof:placetype": "custom",
    "wof:placetype_alt": "airline",
    "wof:subordinate_of": [
      1159288169
    ]
  },
  "geometry": {"coordinates":[-96.999668,39.715956],"type":"Point"}
}
