{
  "type": "Feature",
  "properties": {
    "iso:country":"BZ",
    "sfomuseum:is_sfo":1,
    "sfomuseum:label":"Belize Airways Limited",
    "sfomuseum:name":"Belize Airways Limited",
    "sfomuseum:placetype":"airline",
    "wof:name":"Belize Airways Limited",
    "wof:placetype":"enterprise",
    "wof:subordinate_of":[
        1159288481
    ]
},
  "geometry": {"coordinates":[-88.714488,17.206637],"type":"Point"}
}