{
  "type": "Feature",
  "properties": {
    "iso:country": "BZ",
    "millsfield:count_images": 2,
    "millsfield:count_objects": 1,
    "sfomuseum:count_objects_public": 0,
    "sfomuseum:is_sfo": 1,
    "sfomuseum:label": "Belize Airways Limited",
    "sfomuseum:name": "Belize Airways Limited",
    "sfomuseum:placetype": "airline",
    "wof:name": "Belize Airways Limited",
    "wof:placetype": "custom",
    "wof:placetype_alt": "airline",
    "wof:subordinate_of": [
      1159288481
    ]
  },
  "geometry": {"coordinates":[-88.714488,17.206637],"type":"Point"}
}
