{
  "type": "Feature",
  "properties": {
    "date:inception_lower": "1962-01-01",
    "date:inception_upper": "1962-12-31",
    "iso:country": "CA",
    "millsfield:count_images": 1,
    "millsfield:count_objects": 1,
    "sfomuseum:count_objects_public": 0,
    "sfomuseum:is_sfo": 1,
    "sfomuseum:label": "Calm Air International",
    "sfomuseum:name": "Calm Air International",
    "sfomuseum:placetype": "airline",
    "wd:airline_hub": [
      "Q2235239"
    ],
    "wd:country": "Q16",
    "wd:instance_of": [
      "Q46970"
    ],
    "wof:name": "Calm Air International",
    "wof:placetype": "custom",
    "wof:placetype_alt": "airline",
    "wof:subordinate_of": [
      1159287977
    ]
  },
  "geometry": {"coordinates":[-112.384858,58.33747],"type":"Point"}
}
